pysmoothstreams/__init__.py
pysmoothstreams/auth.py
pysmoothstreams/exceptions.py
pysmoothstreams/guide.py
pysmoothstreams/playlist.py
tests/__init__.py
tests/test_auth.py
tests/test_guide.py
tests/test_playlist.py
pysmoothstreams-0.18.dist-info/LICENSE
pysmoothstreams-0.18.dist-info/METADATA
pysmoothstreams-0.18.dist-info/WHEEL
pysmoothstreams-0.18.dist-info/top_level.txt
pysmoothstreams-0.18.dist-info/RECORD
