Metadata-Version: 2.1
Name: pysmoothstreams
Version: 0.18
Summary: A Python library for SmoothStreams
Home-page: https://github.com/aaearon/pysmoothstreams
Author: Tim Schindler
Author-email: tim@iosharp.com
License: MIT
Platform: UNKNOWN
Classifier: Programming Language :: Python :: 3 :: Only
License-File: LICENSE
